lzhminifluxapi/__init__.py
lzhminifluxapi-0.1.0.dist-info/METADATA
lzhminifluxapi-0.1.0.dist-info/WHEEL
lzhminifluxapi-0.1.0.dist-info/top_level.txt
lzhminifluxapi-0.1.0.dist-info/RECORD
