Metadata-Version: 2.4
Name: lzhminifluxapi
Version: 0.1.0
Summary: 获取`MiniFlux`数据库中对应`site_url`的订阅源中已有的`link`的列表
Author-email: lzh <zhhtdm@hotmail.com>
License: MIT
Project-URL: Homepage, https://github.com/zhhtdm/miniflux-api
Project-URL: Repository, https://github.com/zhhtdm/miniflux-api
Requires-Python: >=3.7
Requires-Dist: asyncpg
